unpacktools/__init__.py
unpacktools/unpack.py
unpacktools-1.0.2.dist-info/LICENSE
unpacktools-1.0.2.dist-info/METADATA
unpacktools-1.0.2.dist-info/WHEEL
unpacktools-1.0.2.dist-info/top_level.txt
unpacktools-1.0.2.dist-info/RECORD
