Metadata-Version: 2.1
Name: unpacktools
Version: 1.0.2
Summary: Try the new iterator-unpacking flavour! Say goodbye to asterisk and welcome the higher readability of unpacktools!
Home-page: https://github.com/SoilLifeL/unpacktools
Author: Toprak Aslan
Author-email: aslantoprak823@gmail.com
License: UNKNOWN
Project-URL: Bug Tracker, https://github.com/SoilLifeL/unpacktools/issues
Platform: UNKNOWN
Classifier: Programming Language :: Python :: 3
Classifier: License :: OSI Approved :: MIT License
Classifier: Operating System :: OS Independent
Requires-Python: >=3.6
License-File: LICENSE
